README.md
setup.py
combo/__init__.py
combo/combo_model.py
combo/config.template.json
combo/default_model.py
combo/main.py
combo/predict.py
combo/common/__init__.py
combo/common/cached_transformers.py
combo/common/logging.py
combo/common/params.py
combo/common/tqdm.py
combo/common/util.py
combo/config/__init__.py
combo/config/exceptions.py
combo/config/from_parameters.py
combo/config/registry.py
combo/data/__init__.py
combo/data/api.py
combo/data/batch.py
combo/data/dataset.py
combo/data/instance.py
combo/data/vocabulary.py
combo/data/dataset_loaders/__init__.py
combo/data/dataset_loaders/data_collator.py
combo/data/dataset_loaders/dataset_loader.py
combo/data/dataset_loaders/simple_data_loader.py
combo/data/dataset_readers/__init__.py
combo/data/dataset_readers/conllu.py
combo/data/dataset_readers/dataset_reader.py
combo/data/dataset_readers/text_classification_json_reader.py
combo/data/dataset_readers/universal_dependencies_dataset_reader.py
combo/data/dataset_readers/utils.py
combo/data/dataset_readers/dataset_utils/__init__.py
combo/data/dataset_readers/dataset_utils/span_utils.py
combo/data/fields/__init__.py
combo/data/fields/adjacency_field.py
combo/data/fields/field.py
combo/data/fields/label_field.py
combo/data/fields/list_field.py
combo/data/fields/metadata_field.py
combo/data/fields/sequence_field.py
combo/data/fields/sequence_label_field.py
combo/data/fields/sequence_multilabel_field.py
combo/data/fields/text_field.py
combo/data/samplers/__init__.py
combo/data/samplers/batch_sampler.py
combo/data/samplers/token_count_batch_sampler.py
combo/data/token_indexers/__init__.py
combo/data/token_indexers/pretrained_transformer_fixed_mismatched_indexer.py
combo/data/token_indexers/pretrained_transformer_indexer.py
combo/data/token_indexers/pretrained_transformer_mismatched_indexer.py
combo/data/token_indexers/single_id_token_indexer.py
combo/data/token_indexers/token_characters_indexer.py
combo/data/token_indexers/token_const_padding_characters_indexer.py
combo_nlp.egg-info/PKG-INFO
combo_nlp.egg-info/SOURCES.txt
combo_nlp.egg-info/dependency_links.txt
combo_nlp.egg-info/entry_points.txt
combo_nlp.egg-info/requires.txt
combo_nlp.egg-info/top_level.txt
